LICENSE
README.md
setup.cfg
setup.py
coinanalyze/colors.py
coinanalyze/exporter.py
coinanalyze/getQuark.py
coinanalyze/getTransactions.py
coinanalyze/prepare.py
coinanalyze/prepareGraph.py
coinanalyze/requester.py
coinanalyze/test_address_list.py
coinanalyze/utils.py
coinanalyze.egg-info/PKG-INFO
coinanalyze.egg-info/SOURCES.txt
coinanalyze.egg-info/dependency_links.txt
coinanalyze.egg-info/requires.txt
coinanalyze.egg-info/top_level.txt