Metadata-Version: 2.1
Name: coinanalyze
Version: 1.0.9
Summary: Coin-help-package For Trading Analyze.
Home-page: UNKNOWN
Author: Zort Labs
License: Python Script
Platform: UNKNOWN
Provides-Extra: dev
License-File: LICENSE
